<annotation>
	<folder></folder>
	<filename>chitrak106_jpg.rf.5ff7473d9fce29b6c97fb5b93af6f777.jpg</filename>
	<path>chitrak106_jpg.rf.5ff7473d9fce29b6c97fb5b93af6f777.jpg</path>
	<source>
		<database>roboflow.com</database>
	</source>
	<size>
		<width>224</width>
		<height>224</height>
		<depth>3</depth>
	</size>
	<segmented>0</segmented>
	<object>
		<name>chitrak</name>
		<pose>Unspecified</pose>
		<truncated>0</truncated>
		<difficult>0</difficult>
		<occluded>0</occluded>
		<bndbox>
			<xmin>81</xmin>
			<xmax>154</xmax>
			<ymin>94</ymin>
			<ymax>174</ymax>
		</bndbox>
	</object>
</annotation>
