<annotation>
	<folder></folder>
	<filename>indian-mallow58_jpg.rf.0d7349778a87767226b3c94207e9168b.jpg</filename>
	<path>indian-mallow58_jpg.rf.0d7349778a87767226b3c94207e9168b.jpg</path>
	<source>
		<database>roboflow.com</database>
	</source>
	<size>
		<width>224</width>
		<height>224</height>
		<depth>3</depth>
	</size>
	<segmented>0</segmented>
	<object>
		<name>indian mallow</name>
		<pose>Unspecified</pose>
		<truncated>0</truncated>
		<difficult>0</difficult>
		<occluded>0</occluded>
		<bndbox>
			<xmin>79</xmin>
			<xmax>142</xmax>
			<ymin>89</ymin>
			<ymax>153</ymax>
		</bndbox>
	</object>
</annotation>
