<annotation>
	<folder></folder>
	<filename>shankupushpam42_jpg.rf.e0121e7b569c8c2d8e4ca73674824833.jpg</filename>
	<path>shankupushpam42_jpg.rf.e0121e7b569c8c2d8e4ca73674824833.jpg</path>
	<source>
		<database>roboflow.com</database>
	</source>
	<size>
		<width>224</width>
		<height>224</height>
		<depth>3</depth>
	</size>
	<segmented>0</segmented>
	<object>
		<name>shankupushpam</name>
		<pose>Unspecified</pose>
		<truncated>0</truncated>
		<difficult>0</difficult>
		<occluded>0</occluded>
		<bndbox>
			<xmin>55</xmin>
			<xmax>153</xmax>
			<ymin>62</ymin>
			<ymax>164</ymax>
		</bndbox>
	</object>
</annotation>
